Metadata-Version: 1.1
Name: aioadb
Version: 0.2.2
Summary: A minimal async adb implementation
Home-page: https://github.com/tba91/aioadb
Author: TBA
Author-email: thiago.brito700@gmail.com
License: MIT
Download-URL: https://github.com/tba91/aioadb/archive/v0.2.2.tar.gz
Keywords: adb,asyncio
Platform: UNKNOWN
Classifier: Development Status :: 3 - Alpha
Classifier: Intended Audience :: Developers
Classifier: Topic :: Software Development :: Build Tools
Classifier: License :: OSI Approved :: MIT License
Classifier: Programming Language :: Python :: 3.7
Classifier: Programming Language :: Python :: 3.8
Classifier: Programming Language :: Python :: 3.9
